.gitignore
LICENSE.txt
README.rst
settings_skel.ini
setup.py
zoodle/__init__.py
zoodle/command.py
zoodle/moodle.py
zoodle/zoodle.py
zoodle.egg-info/PKG-INFO
zoodle.egg-info/SOURCES.txt
zoodle.egg-info/dependency_links.txt
zoodle.egg-info/entry_points.txt
zoodle.egg-info/requires.txt
zoodle.egg-info/top_level.txt
zoodle/commands/__init__.py
zoodle/commands/checklogin.py
zoodle/commands/courses.py
zoodle/commands/userlist.py
zoodle/commands/templates/classlist.txt
zoodle/commands/templates/list.txt
zoodle/commands/templates/plaintext_base.txt
zoodle/commands/templates/signinsheet.txt
zoodle/tests/__init__.py
zoodle/tests/moodle_test.py