Metadata-Version: 1.1
Name: zoodle
Version: 1.1.7
Summary: command-line Moodle query tool
Home-page: https://github.com/peadargrant/zoodle
Author: Peadar Grant
Author-email: peadargrant@gmail.com
License: GPLv3+
Keywords: moodle
Platform: UNKNOWN
Classifier: Development Status :: 3 - Alpha
Classifier: Intended Audience :: Education
Classifier: Topic :: Software Development :: Build Tools
Classifier: License :: OSI Approved :: GNU General Public License v3 or later (GPLv3+)
Classifier: Programming Language :: Python :: 3.5
